expect/__init__.py
expect/api.py
expect/context.py
expect/engine.py
expect/report.py
expect/targets/__init__.py
expect/targets/dir.py
expect/targets/file.py
expect/targets/rule_helpers.py
expect/targets/rules.py
expectfs-0.1.3.dist-info/licenses/LICENSE
expectfs-0.1.3.dist-info/METADATA
expectfs-0.1.3.dist-info/WHEEL
expectfs-0.1.3.dist-info/top_level.txt
expectfs-0.1.3.dist-info/RECORD
