Metadata-Version: 2.4
Name: expectfs
Version: 0.1.3
Summary: Declarative validation for files, directories, and system expectations
Author: Robert Greenslade
License-Expression: MIT
Keywords: validation,filesystem,testing,expectations
Requires-Python: >=3.12
License-File: LICENSE
Provides-Extra: dev
Requires-Dist: pytest>=9.0; extra == "dev"
Dynamic: license-file
